firefly_client/__init__.py
firefly_client/env.py
firefly_client/fc_utils.py
firefly_client/ffws.py
firefly_client/firefly_client.py
firefly_client/plot.py
firefly_client/range_values.py
firefly_client-3.4.0.dist-info/METADATA
firefly_client-3.4.0.dist-info/WHEEL
firefly_client-3.4.0.dist-info/top_level.txt
firefly_client-3.4.0.dist-info/RECORD
