Metadata-Version: 2.4
Name: firefly_client
Version: 3.4.0
Summary: Python API for Firefly: display astronomical data as tables, images, charts, and more!
Author: IPAC Firefly Developers
License: Copyright © <2014>, California Institute of Technology, developed for the 
Project-URL: Homepage, https://github.com/Caltech-IPAC/firefly_client
Project-URL: Documentation, https://caltech-ipac.github.io/firefly_client
Project-URL: Repository, http://github.com/Caltech-IPAC/firefly_client.git
Keywords: jupyter,firefly,caltech,ipac,astronomy,visualization,images,charts,tables
Classifier: Intended Audience :: Developers
Classifier: Intended Audience :: Science/Research
Classifier: Framework :: Jupyter
Classifier: Framework :: Jupyter :: JupyterLab
Classifier: Topic :: Scientific/Engineering :: Astronomy
Classifier: Topic :: Scientific/Engineering :: Visualization
Classifier: Programming Language :: Python
Classifier: Programming Language :: Python :: 3
Requires-Python: >=3.10
Requires-Dist: websocket-client
Requires-Dist: requests
Provides-Extra: docs
Requires-Dist: Sphinx~=7.1.0; extra == "docs"
Requires-Dist: sphinx-automodapi; extra == "docs"
Requires-Dist: pydata-sphinx-theme; extra == "docs"
Requires-Dist: myst-parser; extra == "docs"
